typewire/__init__.py
typewire/caster.py
typewire/forward_refs.py
typewire/identifier.py
typewire/py.typed
typewire/typed_dict.py
typewire-1.3.0.dist-info/METADATA
typewire-1.3.0.dist-info/WHEEL
typewire-1.3.0.dist-info/licenses/LICENSE
typewire-1.3.0.dist-info/RECORD
