Metadata-Version: 2.4
Name: typewire
Version: 1.3.0
Summary: A utility to allow better runtime handling of types by providing a predictable way of transforming data into the shape of a given type hint.
Project-URL: repository, https://github.com/lilellia/typewire
Project-URL: Bug Tracker, https://github.com/lilellia/typewire/issues
Author-email: Lily Ellington <lilell_@outlook.com>
License-File: LICENSE
Keywords: annotated,casting,runtime-types,type-casting,type-hints,typing
Classifier: Development Status :: 5 - Production/Stable
Classifier: Intended Audience :: Developers
Classifier: License :: OSI Approved :: MIT License
Classifier: Operating System :: OS Independent
Classifier: Programming Language :: Python
Classifier: Programming Language :: Python :: 3
Classifier: Programming Language :: Python :: 3.10
Classifier: Programming Language :: Python :: 3.11
Classifier: Programming Language :: Python :: 3.12
Classifier: Programming Language :: Python :: 3.13
Classifier: Programming Language :: Python :: 3.14
Classifier: Topic :: Software Development :: Libraries :: Python Modules
Classifier: Typing :: Typed
Requires-Python: >=3.10
Requires-Dist: typing-extensions>=4.0; python_version < '3.11'
